bitwarden_to_keepass/__init__.py
bitwarden_to_keepass/cli.py
bitwarden_to_keepass/main.py
bitwarden_to_keepass-1.0.0.dist-info/LICENSE
bitwarden_to_keepass-1.0.0.dist-info/METADATA
bitwarden_to_keepass-1.0.0.dist-info/WHEEL
bitwarden_to_keepass-1.0.0.dist-info/entry_points.txt
bitwarden_to_keepass-1.0.0.dist-info/top_level.txt
bitwarden_to_keepass-1.0.0.dist-info/RECORD
