Metadata-Version: 2.1
Name: bitwarden-to-keepass
Version: 1.0.0
Summary: A simple little script that backs up a Bitwarden vault to a local KeePass file.
Author: Douglas Thor
Author-email: Douglas Thor <doug.thor@gmail.com>
License: MIT License
Project-URL: Source Code, https://github.com/dougthor42/bitwarden_to_keepass
Project-URL: Changelog, https://github.com/dougthor42/bitwarden_to_keepass/blob/master/CHANGELOG.md
Project-URL: Bug Tracker, https://github.com/dougthor42/bitwarden_to_keepass/issues
Requires-Python: >=3.8
License-File: LICENSE
Requires-Dist: click (<9.0,>=8.1)
Requires-Dist: pykeepass (<5.0,>=4.0)
Provides-Extra: build
Requires-Dist: build (==0.10.0) ; extra == 'build'
Requires-Dist: setuptools (==65.5.0) ; extra == 'build'
Requires-Dist: wheel (==0.37.1) ; extra == 'build'
Provides-Extra: dev
Requires-Dist: appdirs (==1.4.3) ; extra == 'dev'
Requires-Dist: attrs (==19.3.0) ; extra == 'dev'
Requires-Dist: cfgv (==3.1.0) ; extra == 'dev'
Requires-Dist: coverage (==5.0.3) ; extra == 'dev'
Requires-Dist: distlib (==0.3.6) ; extra == 'dev'
Requires-Dist: filelock (==3.8.0) ; extra == 'dev'
Requires-Dist: identify (==2.5.6) ; extra == 'dev'
Requires-Dist: importlib-metadata (==1.5.0) ; extra == 'dev'
Requires-Dist: importlib-resources (==1.0.2) ; extra == 'dev'
Requires-Dist: more-itertools (==8.2.0) ; extra == 'dev'
Requires-Dist: nodeenv (==1.3.5) ; extra == 'dev'
Requires-Dist: packaging (==20.1) ; extra == 'dev'
Requires-Dist: platformdirs (==2.5.2) ; extra == 'dev'
Requires-Dist: pluggy (==0.13.1) ; extra == 'dev'
Requires-Dist: pre-commit (==2.20.0) ; extra == 'dev'
Requires-Dist: py (==1.10.0) ; extra == 'dev'
Requires-Dist: pykeepass (==4.0.3) ; extra == 'dev'
Requires-Dist: pyparsing (==2.4.6) ; extra == 'dev'
Requires-Dist: pytest (==5.3.5) ; extra == 'dev'
Requires-Dist: pytest-cov (==2.8.1) ; extra == 'dev'
Requires-Dist: PyYAML (==5.4) ; extra == 'dev'
Requires-Dist: six (==1.14.0) ; extra == 'dev'
Requires-Dist: toml (==0.10.0) ; extra == 'dev'
Requires-Dist: virtualenv (==20.16.5) ; extra == 'dev'
Requires-Dist: wcwidth (==0.1.8) ; extra == 'dev'
Requires-Dist: zipp (==3.0.0) ; extra == 'dev'
